MLVisualizationTools/__init__.py
MLVisualizationTools/backend.py
MLVisualizationTools/colorizers.py
MLVisualizationTools/dashbackend.py
MLVisualizationTools/datainterface.py
MLVisualizationTools/graphinterface.py
MLVisualizationTools/modelanalytics.py
MLVisualizationTools/modelinterface.py
MLVisualizationTools/removefeature.py
MLVisualizationTools/types.py
MLVisualizationTools/examples/AnimationDemo.py
MLVisualizationTools/examples/DashDemo.py
MLVisualizationTools/examples/DashKaggleDemo.py
MLVisualizationTools/examples/DashNotebookDemo.py
MLVisualizationTools/examples/DataOverlayDemo.py
MLVisualizationTools/examples/Demo.py
MLVisualizationTools/examples/MatplotlibDemo.py
MLVisualizationTools/examples/RemoveFeatureDemo.py
MLVisualizationTools/examples/SklearnDemo.py
MLVisualizationTools/examples/TrainTitanicModel.py
MLVisualizationTools/examples/Datasets/Titanic/TitanicDemoPreprocess.py
MLVisualizationTools/examples/Datasets/Titanic/train.csv
MLVisualizationTools/examples/Datasets/Titanic/train_orig.csv
MLVisualizationTools/examples/Models/titanicmodel.keras
MLVisualizationTools/examples/Models/titanicmodel_old/fingerprint.pb
MLVisualizationTools/examples/Models/titanicmodel_old/keras_metadata.pb
MLVisualizationTools/examples/Models/titanicmodel_old/saved_model.pb
MLVisualizationTools/examples/Models/titanicmodel_old/variables/variables.data-00000-of-00001
MLVisualizationTools/examples/Models/titanicmodel_old/variables/variables.index
MLVisualizationTools/express/DashModelVisualizer.py
MLVisualizationTools/express/__init__.py
MLVisualizationTools/theme_assets/dark_assets/darktheme.css
MLVisualizationTools/theme_assets/light_assets/lighttheme.css
mlvisualizationtools-0.7.5.dist-info/licenses/LICENSE
mlvisualizationtools-0.7.5.dist-info/METADATA
mlvisualizationtools-0.7.5.dist-info/WHEEL
mlvisualizationtools-0.7.5.dist-info/top_level.txt
mlvisualizationtools-0.7.5.dist-info/RECORD
