Metadata-Version: 2.4
Name: MLVisualizationTools
Version: 0.7.5
Summary: A set of functions and demos to make machine learning projects easier to understand through effective visualizations.
Home-page: https://github.com/RobertJN64/MLVisualizationTools
Author: Robert Nies
Author-email: robertjnies@gmail.com
License: MIT
Classifier: Programming Language :: Python
Classifier: Programming Language :: Python :: 3
Classifier: Programming Language :: Python :: 3 :: Only
Classifier: Programming Language :: Python :: 3.8
Classifier: Programming Language :: Python :: 3.9
Classifier: Programming Language :: Python :: 3.10
Classifier: Programming Language :: Python :: 3.11
Classifier: Programming Language :: Python :: 3.12
Requires-Python: >=3.8
License-File: LICENSE
Requires-Dist: pandas
Provides-Extra: dash
Requires-Dist: dash; extra == "dash"
Requires-Dist: plotly; extra == "dash"
Requires-Dist: dash-bootstrap-components>=1.0.0; extra == "dash"
Requires-Dist: dash-tour-component; extra == "dash"
Provides-Extra: dash-notebook
Requires-Dist: MLVisualizationTools[dash]; extra == "dash-notebook"
Requires-Dist: jupyter-dash; extra == "dash-notebook"
Provides-Extra: ngrok-tunneling
Requires-Dist: MLVisualizationTools[dash-notebook]; extra == "ngrok-tunneling"
Requires-Dist: pyngrok; extra == "ngrok-tunneling"
Provides-Extra: dev
Requires-Dist: MLVisualizationTools[dash]; extra == "dev"
Requires-Dist: pytest; extra == "dev"
Dynamic: license-file
